nosypy/__init__.py
nosypy/annotate.py
nosypy/autoencoder.py
nosypy/data.py
nosypy/run.py
nosypy/image/__init__.py
nosypy/image/apply.py
nosypy/image/calc.py
nosypy/image/convert.py
nosypy/image/filter.py
nosypy/image/io.py
nosypy/image/resize.py
nosypy/image/tile.py
nosypy/novelty/__init__.py
nosypy/novelty/patch.py
nosypy/visualise/__init__.py
nosypy/visualise/draw.py
nosypy/visualise/tiles..py
nosypy_gpu-0.0.2.dist-info/DESCRIPTION.rst
nosypy_gpu-0.0.2.dist-info/METADATA
nosypy_gpu-0.0.2.dist-info/RECORD
nosypy_gpu-0.0.2.dist-info/WHEEL
nosypy_gpu-0.0.2.dist-info/metadata.json
nosypy_gpu-0.0.2.dist-info/top_level.txt
